alphascore/__init__.py
alphascore/checks.py
alphascore/cli.py
alphascore/scoring.py
alphascore/utils.py
alphascore-3.0.dist-info/licenses/LICENSE
alphascore-3.0.dist-info/METADATA
alphascore-3.0.dist-info/WHEEL
alphascore-3.0.dist-info/entry_points.txt
alphascore-3.0.dist-info/top_level.txt
alphascore-3.0.dist-info/RECORD
