Metadata-Version: 2.4
Name: alphascore
Version: 3.0
Summary: AlphaScore v3.0 — Advanced Data Quality Scoring Engine
Author: Shivam Mishra
Author-email: Shivam Mishra <alphaq@duck.com>
License: MIT
Requires-Python: >=3.8
License-File: LICENSE
Requires-Dist: pandas>=1.3
Requires-Dist: jinja2>=3.0
Dynamic: license-file
